Metadata-Version: 1.1
Name: setor
Version: 1.5
Summary: Bot TOR to visit the webpages with unique IP's and random times.
Home-page: https://github.com/agusmakmun/setor/
Author: Agus Makmun (Summon Agus)
Author-email: ags@dracos-linux.id
License: MIT
Download-URL: https://github.com/agusmakmun/setor/tarball/v1.4
Keywords: SETOR,SEO TOR,Bot TOR
Platform: Linux
Classifier: Development Status :: 5 - Production/Stable
Classifier: License :: OSI Approved :: MIT License
Classifier: Operating System :: POSIX :: Linux
Classifier: Intended Audience :: Developers
Classifier: Programming Language :: Python :: 2
Classifier: Programming Language :: Python :: 2.6
Classifier: Programming Language :: Python :: 2.7
Classifier: Topic :: Internet :: WWW/HTTP
Classifier: Topic :: System :: Networking
